[
    {
        "name": "热门",
        "newsList": [
            {
                "_id": "62ffafec3552ddca2cf271a5",
                "title": "展示手游MOBA玩家风采，《王者荣耀》视频大赛正式开赛！\n\n11/27",
                "categories": [
                    {
                        "_id": "62ffa7923cfab00c6012ce82",
                        "name": "公告",
                        "parentName": "62fbbc0bd2e2e7a71328d07a",
                        "__v": 0
                    }
                ],
                "__v": 0,
                "createdAt": "2022-08-19T15:44:44.994Z",
                "updatedAt": "2022-08-19T15:44:44.994Z",
                "categoryName": "公告"
            },
            {
                "_id": "62ffafec3552ddca2cf2719c",
                "title": "【峡谷问答室】第4期：铁血军团JC的秘密，你好奇什么？\n\n10/31",
                "categories": [
                    {
                        "_id": "62ffa7883cfab00c6012ce77",
                        "name": "新闻",
                        "parentName": "62fbbc0bd2e2e7a71328d07a",
                        "__v": 0
                    }
                ],
                "__v": 0,
                "createdAt": "2022-08-19T15:44:44.984Z",
                "updatedAt": "2022-08-19T15:44:44.984Z",
                "categoryName": "新闻"
            },
            {
                "_id": "62ffafec3552ddca2cf2719c",
                "title": "【峡谷问答室】第4期：铁血军团JC的秘密，你好奇什么？\n\n10/31",
                "categories": [
                    {
                        "_id": "62ffa7883cfab00c6012ce77",
                        "name": "新闻",
                        "parentName": "62fbbc0bd2e2e7a71328d07a",
                        "__v": 0
                    }
                ],
                "__v": 0,
                "createdAt": "2022-08-19T15:44:44.984Z",
                "updatedAt": "2022-08-19T15:44:44.984Z",
                "categoryName": "新闻"
            },
            {
                "_id": "62ffafec3552ddca2cf2719c",
                "title": "【峡谷问答室】第4期：铁血军团JC的秘密，你好奇什么？\n\n10/31",
                "categories": [
                    {
                        "_id": "62ffa7883cfab00c6012ce77",
                        "name": "新闻",
                        "parentName": "62fbbc0bd2e2e7a71328d07a",
                        "__v": 0
                    }
                ],
                "__v": 0,
                "createdAt": "2022-08-19T15:44:44.984Z",
                "updatedAt": "2022-08-19T15:44:44.984Z",
                "categoryName": "新闻"
            },
            {
                "_id": "62ffafec3552ddca2cf2719c",
                "title": "【峡谷问答室】第4期：铁血军团JC的秘密，你好奇什么？\n\n10/31",
                "categories": [
                    {
                        "_id": "62ffa7883cfab00c6012ce77",
                        "name": "新闻",
                        "parentName": "62fbbc0bd2e2e7a71328d07a",
                        "__v": 0
                    }
                ],
                "__v": 0,
                "createdAt": "2022-08-19T15:44:44.984Z",
                "updatedAt": "2022-08-19T15:44:44.984Z",
                "categoryName": "新闻"
            }
        ]
    },
    {
        "_id": "62ffa7883cfab00c6012ce77",
        "name": "新闻",
        "parentName": "62fbbc0bd2e2e7a71328d07a",
        "__v": 0,
        "newsList": [
            {
                "_id": "62ffafec3552ddca2cf2719c",
                "title": "【峡谷问答室】第4期：铁血军团JC的秘密，你好奇什么？\n\n10/31",
                "categories": [
                    "62ffa7883cfab00c6012ce77"
                ],
                "__v": 0,
                "createdAt": "2022-08-19T15:44:44.984Z",
                "updatedAt": "2022-08-19T15:44:44.984Z",
                "categoryName": "新闻"
            },
            {
                "_id": "62ffafec3552ddca2cf2719d",
                "title": "KPL日报：eStarPro2:0横扫AS仙阁，小渝强势回归i射手位\n\n09/23",
                "categories": [
                    "62ffa7883cfab00c6012ce77"
                ],
                "__v": 0,
                "createdAt": "2022-08-19T15:44:44.985Z",
                "updatedAt": "2022-08-19T15:44:44.985Z",
                "categoryName": "新闻"
            },
            {
                "_id": "62ffafec3552ddca2cf2719e",
                "title": "《王者荣耀》评测：注意！这不是演习！\n\n12/04",
                "categories": [
                    "62ffa7883cfab00c6012ce77"
                ],
                "__v": 0,
                "createdAt": "2022-08-19T15:44:44.985Z",
                "updatedAt": "2022-08-19T15:44:44.985Z",
                "categoryName": "新闻"
            },
            {
                "_id": "62ffafec3552ddca2cf2719f",
                "title": "《王者荣耀》试玩评测 跨区开黑享受五人团战\n\n12/03",
                "categories": [
                    "62ffa7883cfab00c6012ce77"
                ],
                "__v": 0,
                "createdAt": "2022-08-19T15:44:44.986Z",
                "updatedAt": "2022-08-19T15:44:44.986Z",
                "categoryName": "新闻"
            },
            {
                "_id": "62ffafec3552ddca2cf271a0",
                "title": "《王者荣耀》公测来袭 新版本深度解析评测\n\n12/02",
                "categories": [
                    "62ffa7883cfab00c6012ce77"
                ],
                "__v": 0,
                "createdAt": "2022-08-19T15:44:44.986Z",
                "updatedAt": "2022-08-19T15:44:44.986Z",
                "categoryName": "新闻"
            }
        ]
    },
    {
        "_id": "62ffa7923cfab00c6012ce82",
        "name": "公告",
        "parentName": "62fbbc0bd2e2e7a71328d07a",
        "__v": 0,
        "newsList": [
            {
                "_id": "62ffafec3552ddca2cf271a5",
                "title": "展示手游MOBA玩家风采，《王者荣耀》视频大赛正式开赛！\n\n11/27",
                "categories": [
                    "62ffa7923cfab00c6012ce82"
                ],
                "__v": 0,
                "createdAt": "2022-08-19T15:44:44.994Z",
                "updatedAt": "2022-08-19T15:44:44.994Z",
                "categoryName": "公告"
            },
            {
                "_id": "62ffafec3552ddca2cf271a6",
                "title": "11月13日无法登录游戏公告\n\n11/16",
                "categories": [
                    "62ffa7923cfab00c6012ce82"
                ],
                "__v": 0,
                "createdAt": "2022-08-19T15:44:44.995Z",
                "updatedAt": "2022-08-19T15:44:44.995Z",
                "categoryName": "公告"
            },
            {
                "_id": "62ffafec3552ddca2cf271a7",
                "title": "11月3日游戏充值异常公告\n\n11/04",
                "categories": [
                    "62ffa7923cfab00c6012ce82"
                ],
                "__v": 0,
                "createdAt": "2022-08-19T15:44:44.995Z",
                "updatedAt": "2022-08-19T15:44:44.995Z",
                "categoryName": "公告"
            },
            {
                "_id": "62ffafec3552ddca2cf271a8",
                "title": "1102-1108限免英雄轮换公告\n\n11/01",
                "categories": [
                    "62ffa7923cfab00c6012ce82"
                ],
                "__v": 0,
                "createdAt": "2022-08-19T15:44:44.995Z",
                "updatedAt": "2022-08-19T15:44:44.995Z",
                "categoryName": "公告"
            },
            {
                "_id": "62ffafec3552ddca2cf271a9",
                "title": "微社区个人中心神秘上线\n\n10/29",
                "categories": [
                    "62ffa7923cfab00c6012ce82"
                ],
                "__v": 0,
                "createdAt": "2022-08-19T15:44:44.995Z",
                "updatedAt": "2022-08-19T15:44:44.995Z",
                "categoryName": "公告"
            }
        ]
    },
    {
        "_id": "62ffa7993cfab00c6012ce8d",
        "name": "活动",
        "parentName": "62fbbc0bd2e2e7a71328d07a",
        "__v": 0,
        "newsList": [
            {
                "_id": "62ffafec3552ddca2cf271ae",
                "title": "玩赚双11 三国驾到\n\n11/10",
                "categories": [
                    "62ffa7993cfab00c6012ce8d"
                ],
                "__v": 0,
                "createdAt": "2022-08-19T15:44:45.002Z",
                "updatedAt": "2022-08-19T15:44:45.002Z",
                "categoryName": "活动"
            },
            {
                "_id": "62ffafec3552ddca2cf271af",
                "title": "《王者荣耀》登顶iOS免费榜 全员福利即将发送\n\n10/27",
                "categories": [
                    "62ffa7993cfab00c6012ce8d"
                ],
                "__v": 0,
                "createdAt": "2022-08-19T15:44:45.003Z",
                "updatedAt": "2022-08-19T15:44:45.003Z",
                "categoryName": "活动"
            },
            {
                "_id": "62ffafed3552ddca2cf271b0",
                "title": "【王者荣耀】定名活动公告\n\n10/25",
                "categories": [
                    "62ffa7993cfab00c6012ce8d"
                ],
                "__v": 0,
                "createdAt": "2022-08-19T15:44:45.003Z",
                "updatedAt": "2022-08-19T15:44:45.003Z",
                "categoryName": "活动"
            },
            {
                "_id": "62ffafed3552ddca2cf271b1",
                "title": "“王者降临”第二周活动公告（10.19-10.26）\n\n10/19",
                "categories": [
                    "62ffa7993cfab00c6012ce8d"
                ],
                "__v": 0,
                "createdAt": "2022-08-19T15:44:45.003Z",
                "updatedAt": "2022-08-19T15:44:45.003Z",
                "categoryName": "活动"
            },
            {
                "_id": "62ffafed3552ddca2cf271b2",
                "title": "1019-1025限免英雄轮换公告\n\n10/18",
                "categories": [
                    "62ffa7993cfab00c6012ce8d"
                ],
                "__v": 0,
                "createdAt": "2022-08-19T15:44:45.004Z",
                "updatedAt": "2022-08-19T15:44:45.004Z",
                "categoryName": "活动"
            }
        ]
    }
]